{
  "project_info": {
    "project_number": "1016120424987",
    "project_id": "chatapp-532b8",
    "storage_bucket": "chatapp-532b8.appspot.com"
  },
  "client": [
    {
      "client_info": {
        "mobilesdk_app_id": "1:1016120424987:android:c3c26834c17aacdaaa16be",
        "android_client_info": {
          "package_name": "com.example.chat_app"
        }
      },
      "oauth_client": [],
      "api_key": [
        {
          "current_key": "AIzaSyD5SLkyh1qkI5jENHvpLXw2WP_ws9-SRms"
        }
      ],
      "services": {
        "appinvite_service": {
          "other_platform_oauth_client": []
        }
      }
    }
  ],
  "configuration_version": "1"
}